certpeek.py
certpeek-2026.1.20.dist-info/METADATA
certpeek-2026.1.20.dist-info/WHEEL
certpeek-2026.1.20.dist-info/entry_points.txt
certpeek-2026.1.20.dist-info/licenses/LICENSE
certpeek-2026.1.20.dist-info/RECORD
