Metadata-Version: 2.4
Name: certpeek
Version: 2026.1.20
Summary: Peeks at certificates exposed by other hosts.
Project-URL: Homepage, https://github.com/magnuswatn/certpeek
Author-email: Magnus Watn <magnus@watn.no>
License: MIT License
License-File: LICENSE
Classifier: License :: OSI Approved :: MIT License
Classifier: Operating System :: OS Independent
Classifier: Programming Language :: Python
Classifier: Programming Language :: Python :: 3
Classifier: Programming Language :: Python :: 3.10
Classifier: Programming Language :: Python :: 3.11
Classifier: Programming Language :: Python :: 3.12
Classifier: Programming Language :: Python :: 3.13
Classifier: Programming Language :: Python :: 3.14
Requires-Python: >=3.10
Requires-Dist: click
Requires-Dist: cryptography>=40.0.0
Requires-Dist: idna>=3.11
Requires-Dist: pyopenssl
